{
  "slug": "fractions-made-easy",
  "title": "לימוד שברים עם פיצה ושוקולד - פעילויות מהמטבח",
  "excerpt": "שברים מפחידים על הנייר, אבל במטבח הם הכי טבעיים. חמש פעילויות מהבית, דוגמה פתורה של חיבור שברים, והטעות הכי נפוצה שכמעט כל ילד עושה.",
  "date": "2026-01-22",
  "readTime": "6 דקות",
  "category": "tips",
  "categoryLabel": "טיפים ושיטות לימוד",
  "image": "/blog/fractions-made-easy.webp",
  "tags": ["שברים", "המחשה"],
  "author": "צוות דפי עבודה חכמים",
  "lastModified": "2026-06-25",
  "content": "<h2>על הדף שברים מפחידים, במטבח הם מובנים מאליהם</h2>\n<p>נראה לי שאין נושא בכיתה ד שמפיל יותר ילדים משברים. וזה מצחיק, כי אנחנו חיים בתוך שברים כל היום. חצי שעה, רבע עוף, שליש כוס שמן, שלושת רבעי הדרך לבית ספר. הילד מבין את כל אלה בלי בעיה. הוא נשבר רק כשרואים את זה כמספר עם קו באמצע.</p>\n<p>אז במקום להילחם בדף, ניקח את השברים בחזרה למקום שבו הם הגיוניים, השיש במטבח. הנה חמש פעילויות שעובדות, וכמעט כולן עם דברים שכבר יש לכם בבית.</p>\n<h3>1. הפיצה היא המורה הכי טובה</h3>\n<p>פיצה שלמה מחולקת לשמיניות. הילד אכל שתי משולשים? אכל שתי שמיניות, כלומר רבע. נשארו שש, כלומר שלושת רבעי הפיצה. פתאום 2 חלקי 8 ו-3 חלקי 4 זה לא תרגיל, זה ארוחת ערב.</p>\n<h3>2. שוקולד וחלוקה הוגנת</h3>\n<p>טבלת שוקולד עם 12 קוביות זה אוצר. רוצים לחלק בין שלושה ילדים בצורה הוגנת? כל אחד מקבל שליש, כלומר ארבע קוביות. וכשמישהו צועק שזה לא הוגן, יש לכם הזדמנות מושלמת להראות ששליש מ-12 זה בדיוק 4.</p>\n<h3>3. קיפולי נייר</h3>\n<p>קחו דף ריק. קיפול אחד באמצע, קיבלנו שני חצאים. עוד קיפול, ארבעה רבעים. עוד אחד, שמיניות. תנו לילד לצבוע חלק אחד בכל שלב ולכתוב את השבר לידו. הוא רואה במו עיניו איך ככל שמחלקים ליותר חלקים, כל חלק קטן יותר. זו תובנה שילדים מתקשים לתפוס בעל פה.</p>\n<h3>4. כוסות מדידה בזמן אפייה</h3>\n<p>אופים עוגה? תנו לילד למדוד. חצי כוס סוכר, רבע כוס שמן, שלושת רבעי כוס קמח. ואז תשאלו, אם המתכון דורש חצי כוס ויש לנו רק כוס רבע, כמה פעמים נמלא? פעמיים. הנה חילוק בשברים, בלי שאמרנו את המילה.</p>\n<h3>5. בואו נחבר שברים באמת: חצי ועוד רבע</h3>\n<p>פה ילדים נופלים, אז ניקח את זה לאט. כמה זה חצי ועוד רבע? אם פשוט מחברים מלמעלה ומלמטה, יוצא 2 חלקי 6, וזה לא נכון. הטעות הזו כל כך נפוצה שכדאי לעצור עליה.</p>\n<p>במקום, נחזור לפיצה. חצי פיצה זה ארבע שמיניות. רבע פיצה זה שתי שמיניות. ביחד? שש שמיניות, כלומר שלושת רבעי פיצה. הסוד הוא להביא את שני השברים לאותו גודל חלקים לפני שמחברים. כשהילד רואה את זה על פיצה, המכנה המשותף מפסיק להיות מילה מפחידה.</p>\n<h3>הטעות שכמעט כל ילד עושה</h3>\n<p>הטעות מספר אחת בשברים: לחבר מונה למונה ומכנה למכנה. שליש ועוד שליש זה שני שליש, לא 2 חלקי 6. אם הילד עושה את זה, אל תתקנו במילים. תחזרו לחפצים, לפיצה או לקוביות השוקולד, ותנו לו לראות לבד שזה לא מסתדר. ההבנה שמגיעה מהיד חזקה פי כמה מתיקון על הדף.</p>\n<h3>שאלות שהורים שואלים</h3>\n<p><strong>מאיזה גיל מתחילים שברים?</strong> מושג השבר הפשוט, חצי ורבע, מופיע כבר בכיתות הנמוכות בחיי היומיום. הפעולות עצמן, חיבור והשוואה, מגיעות בכיתות ג-ד.</p>\n<p><strong>הילד מבין במטבח אבל נופל בדף, למה?</strong> כי הקפיצה למספר מופשט קשה. תעשו את הגשר לאט, ציירו את הפיצה ליד התרגיל הכתוב, עד שהוא כבר לא צריך את הציור.</p>\n<p><strong>איך מתרגלים אחרי שהבינו?</strong> כשההבנה כבר שם, עוברים לתרגול מסודר. אפשר לבנות שברים ולהשוות אותם <a href='/play/fraction-build'>במשחק השברים התלת-ממדי</a>, ליצור דפי תרגול <a href='/fractions'>במחולל השברים</a>, ולקרוא מדריך מורחב על <a href='/help/fractions'>איך מלמדים שברים</a> בלי דמעות.</p>"
}
