{
  "slug": "metric-system-guide",
  "title": "טבלת ההמרות שצריך לתלות על הקיר - מדידות אורך",
  "excerpt": "מילימטר, סנטימטר, מטר, קילומטר. הסולם העשרוני שמסדר הכל, משפט זכירה פשוט, דוגמאות פתורות של המרה, והטעות הנפוצה שמבלבלת כיוונים.",
  "date": "2026-03-08",
  "readTime": "5 דקות",
  "category": "curriculum",
  "categoryLabel": "תוכנית הלימודים",
  "image": "/blog/metric-system-guide.webp",
  "tags": ["מדידות", "המרות"],
  "author": "צוות דפי עבודה חכמים",
  "lastModified": "2026-06-25",
  "content": "<h2>הכל פה עשרוני, וזה דווקא חדשות טובות</h2>\n<p>המרות אורך מבלבלות הרבה ילדים, אבל יש בהן יופי אחד גדול, הכל עובד בעשר. בניגוד לשעות ודקות או לחודשים, פה כל מדרגה היא פי עשר מהקודמת. ברגע שהילד תופס את הסולם הזה, רוב הבלבול נעלם.</p>\n<h3>הסולם, מלמטה למעלה</h3>\n<ul>\n<li>10 מילימטר שווים 1 סנטימטר.</li>\n<li>100 סנטימטר שווים 1 מטר.</li>\n<li>1000 מטר שווים 1 קילומטר.</li>\n</ul>\n<p>שווה לתלות את זה על הקיר ליד שולחן הלימודים. כשהילד רואה את הסולם מול העיניים, הוא מפסיק לנחש.</p>\n<h3>משפט זכירה לכיוון</h3>\n<p>הבלבול הגדול הוא לאן להזיז את הנקודה. הכלל פשוט, כשהולכים ליחידה קטנה יותר, המספר גדל, וכשהולכים ליחידה גדולה יותר, המספר קטן. מטר זה הרבה סנטימטרים, אז ממטר לסנטימטר מכפילים. הגיוני, כי בסנטימטרים קטנים צריך הרבה יותר מהם.</p>\n<h3>בואו נמיר ביחד</h3>\n<p>כמה סנטימטרים יש ב-2.5 מטר? הולכים ליחידה קטנה יותר, אז מכפילים ב-100. 2.5 כפול 100 שווה 250 סנטימטר.</p>\n<p>ולכיוון השני, כמה מטרים יש ב-3000 מילימטר? קודם ממילימטר לסנטימטר, מחלקים ב-10, מקבלים 300 סנטימטר. ואז לסנטימטר למטר, מחלקים ב-100, מקבלים 3 מטר. שני צעדים קטנים במקום קפיצה אחת מבלבלת.</p>\n<h3>הטעות הכי נפוצה</h3>\n<p>ילדים מזיזים את הנקודה לכיוון הלא נכון, ומקבלים מספר הזוי, נגיד שאדם בגובה 1.7 מילימטר. פה נכנס טריק חשוב, בדיקת היגיון. תמיד לשאול, התשובה הגיונית? אם יצא שילד בגובה 170 מטר, ברור שמשהו התהפך. ההיגיון הוא בלם הביטחון.</p>\n<h3>אותו רעיון עובד גם במשקל ובנפח</h3>\n<p>היופי בשיטה המטרית הוא שהיא חוזרת על עצמה. מה שעובד באורך עובד גם במשקל ובנפח, באותו סולם של עשר ומאה ואלף. 1000 גרם שווים קילוגרם אחד, בדיוק כמו ש-1000 מטר שווים קילומטר. 1000 מיליליטר שווים ליטר אחד. ברגע שהילד תופס את ההיגיון של הסולם פעם אחת, הוא יכול להחיל אותו על כל סוג מדידה. זה ההבדל בין לשנן שלוש טבלאות נפרדות לבין להבין רעיון אחד שמשרת את כולן.</p>\n<h3>שאלות שהורים שואלים</h3>\n<p><strong>מאיזה גיל לומדים המרות?</strong> מדידות בסיסיות מופיעות כבר בכיתות הנמוכות, אבל המרות עם הזזת נקודה עשרונית מגיעות בכיתות ד-ה, יחד עם המספרים העשרוניים.</p>\n<p><strong>הילד יודע את הטבלה אבל מתבלבל בכיוון, למה?</strong> כי שינן בלי להבין. תחזרו לרעיון הבסיסי, יחידה קטנה דורשת יותר ממנה, ולכן המספר גדל. כשזה מובן, הכיוון מסתדר לבד.</p>\n<p><strong>איך מתרגלים?</strong> כדאי גם למדוד דברים אמיתיים בבית עם סרגל וסרט מדידה, וגם ליצור תרגילי המרה <a href='/units'>במחולל ההמרות</a> כדי לקבע את השיטה.</p>"
}
