{
  "slug": "division",
  "title": "Деление",
  "shortDescription": "Деление — это операция, обратная умножению. Дети учатся делить количество на равные части.",
  "importance": "Деление необходимо для справедливого распределения, вычисления средних значений, а также для понимания дробей и процентов в дальнейшем.",
  "howToTeach": [
    "Начните с реального деления: «Раздели 12 конфет между 3 детьми»",
    "Покажите связь с умножением: если 3×4=12, то 12÷3=4",
    "Сначала практикуйте деление без остатка, затем переходите к делению с остатком",
    "Объясняйте деление в столбик постепенно, на простых числах"
  ],
  "examples": [
    {
      "problem": "24 ÷ 6 = ?",
      "solution": "4",
      "explanation": "Сколько раз 6 содержится в 24? 6×4=24, значит 24÷6=4."
    },
    {
      "problem": "84 ÷ 7 = ?",
      "solution": "12",
      "explanation": "Деление в столбик: 7 содержится в 8 один раз (7), остаток 1. Сносим 4, получаем 14. 7 содержится в 14 два раза (14). Ответ: 12."
    }
  ],
  "commonMistakes": [
    "Путают делимое и делитель",
    "Забывают проверить ответ умножением",
    "Ошибки в делении в столбик из-за пропуска шагов"
  ],
  "parentTips": [
    "Всегда проверяйте умножением: если 24÷6=4, то 6×4 должно быть равно 24",
    "Практикуйтесь, деля конфеты или игрушки",
    "При делении в столбик — действуйте шаг за шагом, не торопитесь"
  ],
  "relatedGeneratorHref": "/worksheet/math?op=div",
  "relatedGeneratorTitle": "Генератор примеров на деление"
}
