{
  "slug": "math-anxiety-tips",
  "title": "5 Tips for Dealing with Math Anxiety in Children",
  "excerpt": "When a child's stomach turns before a math test, that is not laziness, it is anxiety. Five things parents can do at home to break the cycle, and the mistakes that quietly make it worse.",
  "date": "2026-01-15",
  "readTime": "6 min read",
  "category": "anxiety",
  "categoryLabel": "Dealing with Difficulty",
  "image": "/blog/math-anxiety-tips.webp",
  "tags": ["anxiety", "parents", "psychology"],
  "author": "Smart Worksheets Team",
  "lastModified": "2026-06-25",
  "content": "<h2>It is not laziness, it is anxiety</h2>\n<p>If your child starts getting a stomachache the night before a math test, you are not imagining it. Math anxiety is a real thing, and researchers have described it for years. It works in a cruel way: the stress grabs the mind, the mind goes blank, the child fails a problem they actually know, and that proves to them all over again that they are no good at this. A closed loop.</p>\n<p>The most important thing to understand is that this has nothing to do with how smart the child is. Bright kids suffer from it just as much. So instead of another hour of forced drilling, here are five things that actually move the needle.</p>\n<h3>1. Turn math into a game</h3>\n<p>Instead of saying let's practice, say let's play. Cards, dice, a board game, or a math game on the screen. When math is tied to fun and not to a test, the brain stops fighting it. We built a library of <a href='/play'>3D math games</a> for exactly this, where kids practice without feeling like they are practicing.</p>\n<h3>2. Praise the effort, not the result</h3>\n<p>Solved it correctly? Great. Did not get it right but tried seriously? Praise the attempt. I can see you worked really hard on this. That is not a slogan, it is a method. A child who feels measured only by correct answers will fear every mistake. A child who knows the effort is valued is willing to try.</p>\n<h3>3. Normalize mistakes</h3>\n<p>A mistake is not a disaster, it is part of the path. Share your own mistakes with your child, including everyday math. I miscalculated at the supermarket today, I thought it came to 40 shekels and it was 52. When a parent makes an error and the sky does not fall, the child learns that they can too.</p>\n<h3>4. Short practice beats a marathon</h3>\n<p>Do not sit for two hours on worksheets in one evening. Ten to fifteen minutes a day is worth far more. The mind absorbs a small dose, rests, and comes back tomorrow willing. A two-hour marathon once a week only strengthens the link between math and misery.</p>\n<h3>5. Start at a level they succeed at</h3>\n<p>This may be the most important one. When a child solves five problems correctly in a row, confidence builds, and confidence is exactly the cure for anxiety. Start below their level, let them taste success, and only then raise the difficulty slowly. You can build a sheet at the precise level in the <a href='/worksheet'>worksheet generator</a> and climb gradually from there.</p>\n<h3>The mistakes that actually make it worse</h3>\n<ul>\n<li><strong>This is easy, why are you upset.</strong> Maybe it is easy for you. For the child right now it is not, and that sentence just tells them something is wrong with them. Respect the difficulty.</li>\n<li><strong>Comparing to siblings or friends.</strong> Look how your sister solves it with no trouble. That is the best fuel anxiety could ask for. Every child has their own pace.</li>\n<li><strong>A parent who is also stressed.</strong> If you are tense next to the homework, the child picks it up instantly. Take a breath before you sit down beside them.</li>\n</ul>\n<h3>Questions parents ask</h3>\n<p><strong>When does this need professional help?</strong> If the child avoids school, cries before every test, or the anxiety leaks into other areas, it is worth talking to the school counselor or an educational psychologist. There is no shame in it.</p>\n<p><strong>Can a child really get over this?</strong> Yes, in most cases completely. Math anxiety feeds on avoidance and repeated failure. Small, repeated successes break it. It takes patience, but it works.</p>\n<p><strong>My child says they are just bad at math, what do I say?</strong> Nobody is born bad at math. Swap I am bad at this for I have not learned this yet. The difference between those two sentences is the whole story.</p>"
}
