{
  "slug": "overcoming-multiplication-fear",
  "title": "التغلب على الخوف من جدول الضرب",
  "excerpt": "هل يبدو جدول الضرب مخيفًا؟ تقسيم المهمة إلى أجزاء صغيرة يجعل التحدي ممكنًا.",
  "date": "2026-01-20",
  "readTime": "3 دقائق",
  "category": "anxiety",
  "categoryLabel": "التعامل مع الصعوبات",
  "image": "/blog/overcoming-multiplication-fear.webp",
  "tags": ["جدول الضرب", "قلق"],
  "author": "فريق أوراق العمل الذكية",
  "lastModified": "2026-01-17",
  "content": "<h2>يبدو كثيرًا فقط</h2>\n<p>جدول الضرب في الواقع أقل بكثير من 100 تمرين إذا أخذنا بعين الاعتبار خاصية الإبدال. 7 ضرب 8 هو نفسه 8 ضرب 7.</p>\n<h3>ابدأوا من السهل</h3>\n<p>مضاعفات 1 و2 و5 و10 سهلة. بمجرد معرفتها، نصف الجدول أصبح في الجيب.</p>"
}
